search_offline_evaluation/__init__.py
search_offline_evaluation/data.py
search_offline_evaluation/main.py
search_offline_evaluation/schemas.py
search_offline_evaluation/cli/data.py
search_offline_evaluation/cli/evaluate.py
search_offline_evaluation/cli/labeling.py
search_offline_evaluation/cli/logs.py
search_offline_evaluation/cli/main.py
search_offline_evaluation/helpers/__init__.py
search_offline_evaluation/helpers/helpers.py
search_offline_evaluation/helpers/misc.py
search_offline_evaluation/labeling/simple.py
search_offline_evaluation/labeling/structured.py
search_offline_evaluation/prompts/__init__.py
search_offline_evaluation/prompts/binary_relevance.prompt
search_offline_evaluation/prompts/multi_degree_relevance.prompt
search_offline_evaluation/prompts/multi_degree_relevance_magic.prompt
search_offline_evaluation/sql/__init__.py
search_offline_evaluation/sql/general_queries.py
search_offline_evaluation/sql/sql_queries.py
search_offline_evaluation/utils/__init__.py
search_offline_evaluation/utils/agent.py
search_offline_evaluation/utils/annotator.py
search_offline_evaluation/utils/data_extraction.py
search_offline_evaluation/utils/evaluation.py
search_offline_evaluation/utils/get_data.py
search_offline_evaluation/utils/logging_config.py
search_offline_evaluation/utils/monitoring.py
search_offline_evaluation/utils/processing.py
search_offline_evaluation/utils/visualization.py
search_offline_evaluation-0.0.1.dist-info/entry_points.txt
search_offline_evaluation-0.0.1.dist-info/WHEEL
search_offline_evaluation-0.0.1.dist-info/METADATA
search_offline_evaluation-0.0.1.dist-info/RECORD
