Metadata-Version: 2.4
Name: search_offline_evaluation
Version: 0.0.1
Summary: Search Extrinsic and Intrinsic Evaluation powered by LLMs
Author: Search
Requires-Python: ~=3.10
Classifier: Programming Language :: Python :: 3
